setup.cfg
setup.py
zmq_object_exchanger/__init__.py
zmq_object_exchanger/zmq_object_exchanger.py
zmq_object_exchanger.egg-info/PKG-INFO
zmq_object_exchanger.egg-info/SOURCES.txt
zmq_object_exchanger.egg-info/dependency_links.txt
zmq_object_exchanger.egg-info/not-zip-safe
zmq_object_exchanger.egg-info/requires.txt
zmq_object_exchanger.egg-info/top_level.txt