Metadata-Version: 1.0
Name: zmq-object-exchanger
Version: 0.1
Summary: Simple and lightweight framework for exchanging Python objects over network.
Home-page: https://github.com/ZdenekM/zmq_object_exchanger
Author: Zdenek Materna
Author-email: zdenek.materna@gmail.com
License: LGPL
Platform: UNKNOWN
